easylogger4dev_alpha/__init__.py
easylogger4dev_alpha/test.py
tests/__init__.py
easylogger4dev_alpha-0.2.5.dist-info/LICENSE.txt
easylogger4dev_alpha-0.2.5.dist-info/METADATA
easylogger4dev_alpha-0.2.5.dist-info/WHEEL
easylogger4dev_alpha-0.2.5.dist-info/top_level.txt
easylogger4dev_alpha-0.2.5.dist-info/RECORD
