Metadata-Version: 2.1
Name: easylogger4dev-alpha
Version: 0.2.5
Summary: A description of your package
Author: DLMR-CODE
Author-email: yuzhihao82@gmail.com
License: MIT
Keywords: log,dev,easy,alpha
Requires-Python: >=3.10
License-File: LICENSE.txt
Requires-Dist: pandas
Requires-Dist: openpyxl
